netdata/__init__.py
netdata/exceptions.py
netdata-1.2.0.dist-info/LICENSE
netdata-1.2.0.dist-info/METADATA
netdata-1.2.0.dist-info/WHEEL
netdata-1.2.0.dist-info/RECORD
